octoxlabs/__init__.py
octoxlabs/exceptions.py
octoxlabs/octoxlabs.py
octoxlabs/service.py
octoxlabs/utils.py
octoxlabs/constants/__init__.py
octoxlabs/constants/paths.py
octoxlabs/models/__init__.py
octoxlabs/models/adapter.py
octoxlabs/models/companies.py
octoxlabs/models/dashboards.py
octoxlabs/models/discovery.py
octoxlabs/models/query.py
octoxlabs/models/users.py
octoxlabs-0.5.1.dist-info/licenses/LICENSE
octoxlabs-0.5.1.dist-info/METADATA
octoxlabs-0.5.1.dist-info/WHEEL
octoxlabs-0.5.1.dist-info/top_level.txt
octoxlabs-0.5.1.dist-info/RECORD
