Metadata-Version: 2.4
Name: octoxlabs
Version: 0.5.1
Summary: py-octoxlabs is an API client for Octox Labs Cyber Security Asset Management platform on python programming language.
Author-email: Octox Labs Development Team <development@octoxlabs.com>
License: MIT License
Project-URL: Homepage, https://github.com/octoxlabs/py-octoxlabs
Classifier: Programming Language :: Python :: 3
Classifier: Operating System :: OS Independent
Requires-Python: >=3.7
License-File: LICENSE
Requires-Dist: requests
Requires-Dist: urllib3
Dynamic: license-file
